{"errors":[],"warnings":[],"namedChunkGroups":{"app":{"chunks":[6,2],"assets":["webpack-runtime-85c8e70464a760fd3396.js","webpack-runtime-85c8e70464a760fd3396.js.map","app-27d3d6c9a75570edf003.js","app-27d3d6c9a75570edf003.js.map"],"children":{},"childAssets":{}},"component---src-pages-404-js":{"chunks":[0,1,3],"assets":["styles.399f619b552a6fd0a09e.css","styles-a4b7d8bc52b9ec4c410a.js","styles-a4b7d8bc52b9ec4c410a.js.map","1-8837d4cd49870b50612a.js","1-8837d4cd49870b50612a.js.map","component---src-pages-404-js-aa8eb63b52dd1acc71bb.js","component---src-pages-404-js-aa8eb63b52dd1acc71bb.js.map"],"children":{},"childAssets":{}},"component---src-pages-index-js":{"chunks":[0,1,7,4],"assets":["styles.399f619b552a6fd0a09e.css","styles-a4b7d8bc52b9ec4c410a.js","styles-a4b7d8bc52b9ec4c410a.js.map","1-8837d4cd49870b50612a.js","1-8837d4cd49870b50612a.js.map","7-3485f156b01e61ccc5e1.js","7-3485f156b01e61ccc5e1.js.map","component---src-pages-index-js-597ff027ab250b74bb56.js","component---src-pages-index-js-597ff027ab250b74bb56.js.map"],"children":{},"childAssets":{}},"pages-manifest":{"chunks":[5],"assets":["pages-manifest-1761bee62fe5685f79fd.js","pages-manifest-1761bee62fe5685f79fd.js.map"],"children":{},"childAssets":{}}},"assetsByChunkName":{"app":["webpack-runtime-85c8e70464a760fd3396.js","app-27d3d6c9a75570edf003.js"],"component---src-pages-404-js":["styles.399f619b552a6fd0a09e.css","styles-a4b7d8bc52b9ec4c410a.js","1-8837d4cd49870b50612a.js","component---src-pages-404-js-aa8eb63b52dd1acc71bb.js"],"component---src-pages-index-js":["styles.399f619b552a6fd0a09e.css","styles-a4b7d8bc52b9ec4c410a.js","1-8837d4cd49870b50612a.js","7-3485f156b01e61ccc5e1.js","component---src-pages-index-js-597ff027ab250b74bb56.js"],"pages-manifest":["pages-manifest-1761bee62fe5685f79fd.js"]}}